Metadata-Version: 2.1
Name: JetBrains-Fleet-Run
Version: 1.0.0
Summary: Easy Python file running in JetBrains Fleet
Home-page: https://github.com/GamerXZEN/jetbrainsfleetrun
Author: GamerXZEN
Author-email: codspecialops@gmail.com
Keywords: jetbrains-fleet,run.json,python
Classifier: Development Status :: 3 - Alpha
Classifier: Intended Audience :: Developers
Classifier: Topic :: Software Development :: Build Tools
Classifier: License :: OSI Approved :: MIT License
Classifier: Programming Language :: Python :: 3.7
Classifier: Programming Language :: Python :: 3.8
Classifier: Programming Language :: Python :: 3.9
Classifier: Programming Language :: Python :: 3.10
Classifier: Programming Language :: Python :: 3.11
Classifier: Programming Language :: Python :: 3.12
